gpp_prediction/__init__.py
gpp_prediction/core.py
gpp_prediction-0.1.5.dist-info/METADATA
gpp_prediction-0.1.5.dist-info/WHEEL
gpp_prediction-0.1.5.dist-info/licenses/LICENSE
gpp_prediction-0.1.5.dist-info/RECORD
