Metadata-Version: 2.4
Name: gpp-prediction
Version: 0.1.5
Summary: A package for the GPP related Assignment 3
Project-URL: Homepage, https://github.com/yourusername/gpp-prediction
Project-URL: Bug Tracker, https://github.com/yourusername/gpp-prediction/issues
Author-email: "Nicolas F. Bader" <nicolas.bader@tuwien.ac.at>
License: MIT License
License-File: LICENSE
Keywords: ecology,environmental science,gpp
Classifier: Development Status :: 3 - Alpha
Classifier: Intended Audience :: Science/Research
Classifier: License :: OSI Approved :: MIT License
Classifier: Programming Language :: Python :: 3.13
Classifier: Topic :: Scientific/Engineering
Requires-Python: >=3.9
Requires-Dist: numpy>=1.26.0
Requires-Dist: pandas>=2.0.0
